./.gitignore
./.pre-commit-config.yaml
./.readthedocs.yaml
./CODE_OF_CONDUCT.rst
./CONTRIBUTING.rst
./LICENSE
./Makefile
./PKG-INFO
./README.rst
./cookiecutter.json
./pyproject.toml
./pytest.ini
./tox.ini
./.github/issue_template.md
./.github/pull_request_template.md
./.github/workflows/ci.yml
./docs/Makefile
./docs/conf.py
./docs/console-script-setup.rst
./docs/index.rst
./docs/prompts.rst
./docs/pypi-release-checklist.rst
./docs/tutorial.rst
./docs/_static/.gitkeep
./hooks/post_gen_project.py
./tests/test_bake_project.py
./{{cookiecutter.project_name}}/.bumpversion.toml
./{{cookiecutter.project_name}}/.gitignore
./{{cookiecutter.project_name}}/.pre-commit-config.yaml
./{{cookiecutter.project_name}}/.readthedocs.yaml
./{{cookiecutter.project_name}}/AUTHORS.rst
./{{cookiecutter.project_name}}/CONTRIBUTING.rst
./{{cookiecutter.project_name}}/HISTORY.rst
./{{cookiecutter.project_name}}/LICENSE
./{{cookiecutter.project_name}}/MANIFEST.in
./{{cookiecutter.project_name}}/Makefile
./{{cookiecutter.project_name}}/README.rst
./{{cookiecutter.project_name}}/pyproject.toml
./{{cookiecutter.project_name}}/tox.ini
./{{cookiecutter.project_name}}/.github/issue_template.md
./{{cookiecutter.project_name}}/.github/pull_request_template.md
./{{cookiecutter.project_name}}/.github/workflows/ci.yml
./{{cookiecutter.project_name}}/.github/workflows/main.yml
./{{cookiecutter.project_name}}/.github/workflows/pages.yml
./{{cookiecutter.project_name}}/docs/Makefile
./{{cookiecutter.project_name}}/docs/authors.rst
./{{cookiecutter.project_name}}/docs/conf.py
./{{cookiecutter.project_name}}/docs/contributing.rst
./{{cookiecutter.project_name}}/docs/history.rst
./{{cookiecutter.project_name}}/docs/index.rst
./{{cookiecutter.project_name}}/docs/installation.rst
./{{cookiecutter.project_name}}/docs/make.bat
./{{cookiecutter.project_name}}/docs/usage.rst
./{{cookiecutter.project_name}}/docs/_static/.gitkeep
./{{cookiecutter.project_name}}/tests/__init__.py
cookiecutter_namespace_template-24.2.0.dist-info/METADATA
cookiecutter_namespace_template-24.2.0.dist-info/WHEEL
cookiecutter_namespace_template-24.2.0.dist-info/licenses/LICENSE
cookiecutter_namespace_template-24.2.0.dist-info/RECORD
