Metadata-Version: 2.3
Name: cookiecutter-namespace-template
Version: 24.2.0
Summary: Cookiecutter template for a Python namespace package
Project-URL: Documentation, https://cookiecutter-namespace-template.readthedocs.io/
Project-URL: Bug Tracker, https://github.com/veit/cookiecutter-namespace-template/issues
Project-URL: Source Code, https://github.com/veit/cookiecutter-namespace-template
Author-email: Veit Schiele <veit@cusy.io>
License-Expression: BSD-3-Clause
License-File: LICENSE
Keywords: cookiecutter,package,template
Classifier: Development Status :: 4 - Beta
Classifier: Environment :: Console
Classifier: Intended Audience :: Developers
Classifier: License :: OSI Approved :: BSD License
Classifier: Natural Language :: English
Classifier: Operating System :: OS Independent
Classifier: Programming Language :: Python
Classifier: Programming Language :: Python :: 3
Classifier: Programming Language :: Python :: 3.9
Classifier: Programming Language :: Python :: 3.10
Classifier: Programming Language :: Python :: 3.11
Classifier: Programming Language :: Python :: 3.12
Classifier: Programming Language :: Python :: 3.13
Classifier: Programming Language :: Python :: Implementation :: CPython
Classifier: Programming Language :: Python :: Implementation :: PyPy
Classifier: Topic :: Software Development :: Libraries :: Python Modules
Requires-Python: >=3.9
Requires-Dist: cookiecutter
Provides-Extra: dev
Requires-Dist: codespell; extra == 'dev'
Requires-Dist: furo; extra == 'dev'
Requires-Dist: pre-commit; extra == 'dev'
Requires-Dist: pytest; extra == 'dev'
Requires-Dist: pytest-cookies; extra == 'dev'
Requires-Dist: sphinx; extra == 'dev'
Requires-Dist: tomli; (python_version < '3.11') and extra == 'dev'
Requires-Dist: tox; extra == 'dev'
Provides-Extra: docs
Requires-Dist: furo; extra == 'docs'
Requires-Dist: sphinx; extra == 'docs'
Provides-Extra: tests
Requires-Dist: pytest; extra == 'tests'
Requires-Dist: pytest-cookies; extra == 'tests'
Requires-Dist: tox; extra == 'tests'
